oneidentity_safeguard_sessions_plugin_sdk-1.9.0.data/data/etc/safeguard/sessions/plugin/Pipfile.lock
oneidentity_safeguard_sessions_plugin_sdk-1.9.0.data/data/etc/safeguard/sessions/plugin/version
oneidentity_safeguard_sessions_plugin_sdk-1.9.0.data/scripts/pluginv
oneidentity_safeguard_sessions_plugin_sdk-1.9.0.dist-info/licenses/LICENSE
safeguard/__init__.py
safeguard/sessions/__init__.py
safeguard/sessions/plugin/__init__.py
safeguard/sessions/plugin/aa_plugin.py
safeguard/sessions/plugin/authentication_cache.py
safeguard/sessions/plugin/box_configuration.py
safeguard/sessions/plugin/box_configuration_settings.py
safeguard/sessions/plugin/connection_info.py
safeguard/sessions/plugin/connection_limiter.py
safeguard/sessions/plugin/credential_store.py
safeguard/sessions/plugin/credential_store_exceptions.py
safeguard/sessions/plugin/credentialstore_plugin.py
safeguard/sessions/plugin/endpoint_extractor.py
safeguard/sessions/plugin/exceptions.py
safeguard/sessions/plugin/host_resolver.py
safeguard/sessions/plugin/lazy_proxy.py
safeguard/sessions/plugin/ldap_server.py
safeguard/sessions/plugin/ldap_server_exceptions.py
safeguard/sessions/plugin/ldap_server_group_list.py
safeguard/sessions/plugin/lockfile.py
safeguard/sessions/plugin/logging.py
safeguard/sessions/plugin/memory_cache.py
safeguard/sessions/plugin/mfa_client.py
safeguard/sessions/plugin/plugin_base.py
safeguard/sessions/plugin/plugin_configuration.py
safeguard/sessions/plugin/plugin_configuration_exceptions.py
safeguard/sessions/plugin/plugin_context.py
safeguard/sessions/plugin/plugin_response.py
safeguard/sessions/plugin/requests_tls.py
safeguard/sessions/plugin/user_list.py
safeguard/sessions/plugin/user_list_exceptions.py
safeguard/sessions/plugin/user_mapping.py
safeguard/sessions/plugin/data/__init__.py
safeguard/sessions/plugin/data/aa_sample.py
safeguard/sessions/plugin_impl/__init__.py
safeguard/sessions/plugin_impl/box_config.py
safeguard/sessions/plugin_impl/credential_store.py
safeguard/sessions/plugin_impl/database.py
safeguard/sessions/plugin_impl/decryptor.py
oneidentity_safeguard_sessions_plugin_sdk-1.9.0.dist-info/METADATA
oneidentity_safeguard_sessions_plugin_sdk-1.9.0.dist-info/WHEEL
oneidentity_safeguard_sessions_plugin_sdk-1.9.0.dist-info/top_level.txt
oneidentity_safeguard_sessions_plugin_sdk-1.9.0.dist-info/RECORD
