Metadata-Version: 2.4
Name: oneidentity_safeguard_sessions_plugin_sdk
Version: 1.9.0
Summary: One Identity Safeguard for Privileged Sessions Plugin SDK
Author: OneIdentity PAM Integration Team
Author-email: QDL.QBU-OI.RD.Safeguard.Integration@oneidentity.com
Classifier: Intended Audience :: Developers
Classifier: Programming Language :: Python :: 3
Classifier: Development Status :: 5 - Production/Stable
Classifier: License :: OSI Approved :: Apache Software License
Classifier: Topic :: Software Development :: Libraries :: Python Modules
Requires-Python: >=3.6
License-File: LICENSE
Requires-Dist: certifi==2025.8.3
Requires-Dist: cffi==1.17.1
Requires-Dist: charset-normalizer==3.4.3
Requires-Dist: coverage==7.10.6
Requires-Dist: cryptography==41.0.7
Requires-Dist: fakeredis==2.31.1
Requires-Dist: flake8==7.3.0
Requires-Dist: idna==3.10
Requires-Dist: iniconfig==2.1.0
Requires-Dist: invoke==2.2.0
Requires-Dist: mccabe==0.7.0
Requires-Dist: multidict==6.6.4
Requires-Dist: packaging==25.0
Requires-Dist: pluggy==1.6.0
Requires-Dist: propcache==0.3.2
Requires-Dist: pyasn1==0.6.1
Requires-Dist: pyasn1-modules==0.4.2
Requires-Dist: pycodestyle==2.14.0
Requires-Dist: pycparser==2.22
Requires-Dist: pyflakes==3.4.0
Requires-Dist: pygments==2.19.2
Requires-Dist: pyopenssl==23.2.0
Requires-Dist: pytest==8.4.2
Requires-Dist: pytest-cov==6.2.1
Requires-Dist: pytest-mock==3.15.0
Requires-Dist: pytest-vcr==1.0.2
Requires-Dist: python-ldap==3.4.4
Requires-Dist: pyyaml==6.0.1
Requires-Dist: redis==6.4.0
Requires-Dist: requests==2.31.0
Requires-Dist: semantic-version==2.10.0
Requires-Dist: sortedcontainers==2.4.0
Requires-Dist: urllib3==2.0.7
Requires-Dist: vcrpy==7.0.0
Requires-Dist: wrapt==1.17.3
Requires-Dist: yarl==1.20.1
Dynamic: author
Dynamic: author-email
Dynamic: classifier
Dynamic: description
Dynamic: description-content-type
Dynamic: license-file
Dynamic: requires-dist
Dynamic: requires-python
Dynamic: summary
